misdeed/OmicsGenerator.py
misdeed/__init__.py
misdeed/inference.py
misdeed/visualization.py
MiSDEED-1.0.3.dist-info/LICENSE
MiSDEED-1.0.3.dist-info/METADATA
MiSDEED-1.0.3.dist-info/WHEEL
MiSDEED-1.0.3.dist-info/top_level.txt
MiSDEED-1.0.3.dist-info/RECORD
